challenge_bypass_ristretto/__init__.py
challenge_bypass_ristretto/_native.py
challenge_bypass_ristretto/_native__ffi.py
challenge_bypass_ristretto/_native__lib.so
challenge_bypass_ristretto/tests/__init__.py
challenge_bypass_ristretto/tests/test_privacypass.py
python_challenge_bypass_ristretto-2022.6.30.dist-info/METADATA
python_challenge_bypass_ristretto-2022.6.30.dist-info/WHEEL
python_challenge_bypass_ristretto-2022.6.30.dist-info/top_level.txt
python_challenge_bypass_ristretto-2022.6.30.dist-info/RECORD
