Metadata-Version: 2.1
Name: python-challenge-bypass-ristretto
Version: 2022.6.30
Summary: Bindings for Brave's Ristretto-flavored Privacy Pass library.
Home-page: https://github.com/LeastAuthority/python-challenge-bypass-ristretto
Author: Ramakrishnan Muthukrishnan
Author-email: ram@leastauthority.com
License: Mozilla Public License v2
Platform: any
Requires-Dist: cffi
Requires-Dist: attrs
Provides-Extra: tests
Requires-Dist: testtools ; extra == 'tests'
Requires-Dist: hypothesis ; extra == 'tests'
